michaelPanLogLib/__init__.py
michaelPanLogLib/logs.py
michaelPanLogLib-0.0.2.dist-info/LICENSE
michaelPanLogLib-0.0.2.dist-info/METADATA
michaelPanLogLib-0.0.2.dist-info/WHEEL
michaelPanLogLib-0.0.2.dist-info/top_level.txt
michaelPanLogLib-0.0.2.dist-info/RECORD
