Metadata-Version: 2.1
Name: michaelPanLogLib
Version: 0.0.2
Summary: all kind of log
Author: chuntong pan
Author-email: panzhang1314@gmail.com
Platform: all
Classifier: Programming Language :: Python :: 3
Classifier: License :: OSI Approved :: MIT License
Classifier: Operating System :: OS Independent
License-File: LICENSE
